[
  {
    "image": "afi.png",
    "gender": "t",
    "audio": "01-afi.mp3"
  },
  {
    "image": "vo.png",
    "gender": "t",
    "audio": "02-vo.mp3"
  },
  {
    "image": "anzib.png",
    "gender": "t",
    "audio": "03-anzib.mp3"
  },
  {
    "image": "agioc.png",
    "gender": "p",
    "audio": "04-agioc.mp3"
  },
  {
    "image": "lonshi.png",
    "gender": "t",
    "audio": "05-lonshi.mp3"
  },
  {
    "image": "aghabi.png",
    "gender": "t",
    "audio": "06-aghabi.mp3"
  },
  {
    "image": "daniel.png",
    "gender": "",
    "audio": "07-daniel.mp3"
  },
  {
    "image": "zibnon.png",
    "gender": "p",
    "audio": "08-zibnon.mp3"
  },
  {
    "image": "sheri.png",
    "gender": "t",
    "audio": "09-sheri.mp3"
  },
  {
    "image": "so-ineft.png",
    "gender": "p",
    "audio": "10-so-ineft.mp3"
  },
  {
    "image": "zenzen.png",
    "gender": "t",
    "audio": "11-zenzen.mp3"
  },
  {
    "image": "eklema.png",
    "gender": "p",
    "audio": "12-eklema.mp3"
  },
  {
    "image": "mashthoti.png",
    "gender": "t",
    "audio": "13-mashthoti.mp3"
  },
  {
    "image": "parthenos.png",
    "gender": "t",
    "audio": "14-parthenos.mp3"
  },
  {
    "image": "ift.png",
    "gender": "p",
    "audio": "15-ift.mp3"
  },
  {
    "image": "wik.png",
    "gender": "p",
    "audio": "16-wik.mp3"
  },
  {
    "image": "aloli.png",
    "gender": "",
    "audio": "17-aloli.mp3"
  },
  {
    "image": "moit.png",
    "gender": "p",
    "audio": "18-moit.mp3"
  },
  {
    "image": "amin.png",
    "gender": "",
    "audio": "19-amin.mp3"
  },
  {
    "image": "liks.png",
    "gender": "p",
    "audio": "20-liks.mp3"
  },
  {
    "image": "gom.png",
    "gender": "t",
    "audio": "21-gom.mp3"
  },
  {
    "image": "kap.png",
    "gender": "p",
    "audio": "22-kap.mp3"
  },
  {
    "image": "ran.png",
    "gender": "p",
    "audio": "23-ran.mp3"
  },
  {
    "image": "esmov.png",
    "gender": "p",
    "audio": "24-esmov.mp3"
  },
  {
    "image": "iot.png",
    "gender": "p",
    "audio": "25-iot.mp3"
  },
  {
    "image": "ebnevma.png",
    "gender": "p",
    "audio": "26-ebnevma.mp3"
  },
  {
    "image": "oro.png",
    "gender": "p",
    "audio": "27-oro.mp3"
  },
  {
    "image": "kethara.png",
    "gender": "t",
    "audio": "28-kethara.mp3"
  },
  {
    "image": "afot.png",
    "gender": "p",
    "audio": "29-afot.mp3"
  },
  {
    "image": "eklom.png",
    "gender": "p",
    "audio": "30-eklom.mp3"
  },
  {
    "image": "psishi.png",
    "gender": "t",
    "audio": "31-psishi.mp3"
  },
  {
    "image": "piekhristoc.png",
    "gender": "p",
    "audio": "32-piekhristoc.mp3"
  },
  {
    "image": "psalmos.png",
    "gender": "p",
    "audio": "33-psalmos.mp3"
  },
  {
    "image": "soni.png",
    "gender": "t",
    "audio": "34-soni.mp3"
  },
  {
    "image": "shiri.png",
    "gender": "p",
    "audio": "35-shiri.mp3"
  },
  {
    "image": "af.png",
    "gender": "p",
    "audio": "36-af.mp3"
  },
  {
    "image": "onkh.png",
    "gender": "p",
    "audio": "37-onkh.mp3"
  },
  {
    "image": "kahi.png",
    "gender": "p",
    "audio": "38-kahi.mp3"
  },
  {
    "image": "kouji.png",
    "gender": "p",
    "audio": "39-kouji.mp3"
  },
  {
    "image": "gwm.png",
    "gender": "p",
    "audio": "40-gwm.mp3"
  },
  {
    "image": "tshoic.png",
    "gender": "p",
    "audio": "41-tshoic.mp3"
  },
  {
    "image": "nouti.png",
    "gender": "p",
    "audio": "42-nouti.mp3"
  }
]
